wild/__init__.py
wild/module.py
dykyi-0.1.dist-info/METADATA
dykyi-0.1.dist-info/WHEEL
dykyi-0.1.dist-info/top_level.txt
dykyi-0.1.dist-info/RECORD
