Metadata-Version: 2.1
Name: dykyi
Version: 0.1
Summary: My personal library for making ml projects easier!
Home-page: https://github.com/dykyivladk1/Wild
Author: Dykyi Vladyslav
Author-email: vladdikiy17@gmail.com
Classifier: Programming Language :: Python :: 3
Classifier: License :: OSI Approved :: MIT License
Classifier: Operating System :: OS Independent
